todoist_api_python/__init__.py
todoist_api_python/api.py
todoist_api_python/api_async.py
todoist_api_python/authentication.py
todoist_api_python/models.py
todoist_api_python/py.typed
todoist_api_python/_core/__init__.py
todoist_api_python/_core/endpoints.py
todoist_api_python/_core/http_headers.py
todoist_api_python/_core/http_requests.py
todoist_api_python/_core/utils.py
todoist_api_python-3.0.1.dist-info/METADATA
todoist_api_python-3.0.1.dist-info/WHEEL
todoist_api_python-3.0.1.dist-info/licenses/LICENSE
todoist_api_python-3.0.1.dist-info/RECORD
