Metadata-Version: 2.4
Name: todoist_api_python
Version: 3.0.1
Summary: Official Python SDK for the Todoist API.
Project-URL: Homepage, https://github.com/Doist/todoist-api-python
Project-URL: Repository, https://github.com/Doist/todoist-api-python
Project-URL: Documentation, https://developer.todoist.com/rest/
Author-email: Doist Developers <dev@doist.com>
License-Expression: MIT
License-File: LICENSE
Keywords: api,python,rest,sync,todoist
Classifier: Intended Audience :: Developers
Classifier: Topic :: Software Development :: Libraries :: Python Modules
Requires-Python: ~=3.9
Requires-Dist: annotated-types
Requires-Dist: dataclass-wizard<1.0,>=0.35.0
Requires-Dist: requests<3,>=2.32.3
